larcoh/__init__.py
larcoh/dataproc.py
larcoh/filetypes.py
larcoh/main.py
larcoh/pipeline.py
larcoh/pipeline_utils.py
larcoh/query_utils.py
larcoh/targets.py
larcoh/types.py
larcoh/utils.py
larcoh/version.py
larcoh-0.1.5.data/scripts/ancestry_pca.py
larcoh-0.1.5.data/scripts/ancestry_plot.py
larcoh-0.1.5.data/scripts/annotate_as.py
larcoh-0.1.5.data/scripts/check_pedigree.py
larcoh-0.1.5.data/scripts/combine_gvcfs.py
larcoh-0.1.5.data/scripts/create_rf_annotations.py
larcoh-0.1.5.data/scripts/evaluation.py
larcoh-0.1.5.data/scripts/final_filter.py
larcoh-0.1.5.data/scripts/final_mt_to_vcf.py
larcoh-0.1.5.data/scripts/generate_freq_data.py
larcoh-0.1.5.data/scripts/generate_info_ht.py
larcoh-0.1.5.data/scripts/generate_variant_qc_annotations.py
larcoh-0.1.5.data/scripts/load_vqsr.py
larcoh-0.1.5.data/scripts/make_finalised_mt.py
larcoh-0.1.5.data/scripts/make_noref_mt.py
larcoh-0.1.5.data/scripts/make_subset_mt.py
larcoh-0.1.5.data/scripts/random_forest.py
larcoh-0.1.5.data/scripts/release_vcf_export_chrom.py
larcoh-0.1.5.data/scripts/sample_qc_flag_related.py
larcoh-0.1.5.data/scripts/sample_qc_hard_filters.py
larcoh-0.1.5.data/scripts/sample_qc_pcrelate.py
larcoh-0.1.5.data/scripts/sample_qc_regressed_filters.py
larcoh-0.1.5.data/scripts/sample_qc_somalier_to_ht.py
larcoh-0.1.5.data/scripts/sample_qc_subset_mt_for_pca.py
larcoh-0.1.5.data/scripts/sample_qc_write_metadata.py
larcoh-0.1.5.data/scripts/siteonly_ht_to_vcf.py
larcoh-0.1.5.data/scripts/variant_qc_plotting.py
larcoh-0.1.5.dist-info/LICENSE
larcoh-0.1.5.dist-info/METADATA
larcoh-0.1.5.dist-info/WHEEL
larcoh-0.1.5.dist-info/top_level.txt
larcoh-0.1.5.dist-info/RECORD
