Metadata-Version: 2.1
Name: larcoh
Version: 0.1.5
Summary: Pipeline for joint calling, sample and variant QC for WGS germline variant calling data in large cohorts
Home-page: https://github.com/populationgenomics/joint-calling
License: MIT
Keywords: bioinformatics
Classifier: Environment :: Console
Classifier: Intended Audience :: Science/Research
Classifier: License :: OSI Approved :: GNU General Public License v3 (GPLv3)
Classifier: Natural Language :: English
Classifier: Operating System :: MacOS :: MacOS X
Classifier: Operating System :: POSIX
Classifier: Operating System :: Unix
Classifier: Programming Language :: Python
Classifier: Topic :: Scientific/Engineering
Classifier: Topic :: Scientific/Engineering :: Bio-Informatics
License-File: LICENSE
Requires-Dist: cpg-utils (>=4.4.5)
Requires-Dist: cpg-pipes
Requires-Dist: analysis-runner
Requires-Dist: sample-metadata
Requires-Dist: hail (>=0.2.97)
Requires-Dist: cpg-gnomad
Requires-Dist: pandas
Requires-Dist: click
Requires-Dist: google-cloud-storage
Requires-Dist: google-cloud-secret-manager
Requires-Dist: coloredlogs
